README.md
setup.py
ser_Stovba/constants.py
ser_Stovba/factory.py
ser_Stovba/json_serializer.py
ser_Stovba/serializersi.py
ser_Stovba/xml_serializer.py
ser_Stovba_lab3.egg-info/PKG-INFO
ser_Stovba_lab3.egg-info/SOURCES.txt
ser_Stovba_lab3.egg-info/dependency_links.txt
ser_Stovba_lab3.egg-info/requires.txt
ser_Stovba_lab3.egg-info/top_level.txt