Metadata-Version: 2.1
Name: ser-Stovba-lab3
Version: 0.1.1
Summary: somme serialization
Author: Stovba Vladislav
Author-email: vlasstovbaboy@mail.ru
License: MIT
Classifier: Intended Audience :: Developers
Classifier: License :: OSI Approved :: MIT License
Classifier: Programming Language :: Python :: 3.10
Classifier: Operating System :: OS Independent
